.travis.yml
LICENSE
README.rst
setup.py
test_triegex.py
triegex/__init__.py
triegex.egg-info/PKG-INFO
triegex.egg-info/SOURCES.txt
triegex.egg-info/dependency_links.txt
triegex.egg-info/top_level.txt